assetoolz/db.py
assetoolz/__init__.py
assetoolz/utils.py
assetoolz/i18n.py
assetoolz/models.py
assetoolz/detour.py
assetoolz/appconf.py
assetoolz/resource.py
assetoolz/compiler.py
assetoolz/assets.py
assetoolz/cache.py
assetoolz/expressions/__init__.py
assetoolz/expressions/stylesheets.py
assetoolz/expressions/scripts.py
assetoolz/expressions/html.py
assetoolz-0.0.7.dist-info/WHEEL
assetoolz-0.0.7.dist-info/DESCRIPTION.rst
assetoolz-0.0.7.dist-info/entry_points.txt
assetoolz-0.0.7.dist-info/METADATA
assetoolz-0.0.7.dist-info/top_level.txt
assetoolz-0.0.7.dist-info/metadata.json
assetoolz-0.0.7.dist-info/RECORD
