Metadata-Version: 2.0
Name: assetoolz
Version: 0.0.7
Summary: Web assets build system
Home-page: https://github.com/aspyatkin/assetoolz
Author: Alexander Pyatkin
Author-email: asp@thexyz.net
License: MIT
Platform: UNKNOWN
Requires-Dist: setuptools (>=5.4)
Requires-Dist: sqlalchemy (>=0.9,<1.0)
Requires-Dist: pyyaml (>=3.11)
Requires-Dist: simplejson (>=3.6,<4.0)
